README.md
setup.cfg
setup.py
mediafier/__init__.py
mediafier.egg-info/PKG-INFO
mediafier.egg-info/SOURCES.txt
mediafier.egg-info/dependency_links.txt
mediafier.egg-info/requires.txt
mediafier.egg-info/top_level.txt
mediafier/image/__init__.py
mediafier/image/checks.py
mediafier/image/color.py
mediafier/image/cropping.py
mediafier/image/draw.py
mediafier/image/modifications.py
mediafier/image/orientation.py
mediafier/image/size.py
mediafier/utils/__init__.py
mediafier/utils/utils.py
mediafier/video/__init__.py
mediafier/video/common.py
tests/__init__.py
tests/test_images_checks.py
tests/test_images_color.py
tests/test_images_cropping.py
tests/test_images_draw.py
tests/test_images_modifications.py
tests/test_images_orientation.py
tests/test_images_size.py
tests/test_video_common.py