Metadata-Version: 1.1
Name: mediafier
Version: 0.1.2
Summary: Python library that helps with media (image/video) transformation and augmentation for machine learning and artificial vision projects. Enables the user to modify media for different purposes, as increasing a dataset or just changing some properties.
Home-page: https://github.com/JParzival/mediafier
Author: JParzival
Author-email: jorge.deandres@hotmail.es
License: MIT
Keywords: IMAGE,VIDEO,MEDIA,TRANSFORMATION,AUGMENTATION
Platform: UNKNOWN
Classifier: Development Status :: 3 - Alpha
Classifier: Intended Audience :: Developers
Classifier: Topic :: Software Development :: Build Tools
Classifier: License :: OSI Approved :: MIT License
Classifier: Programming Language :: Python :: 3
